slickpay/__init__.py
slickpay/merchant.py
slickpay/user.py
slick_pay-0.3.dist-info/LICENSE.txt
slick_pay-0.3.dist-info/METADATA
slick_pay-0.3.dist-info/WHEEL
slick_pay-0.3.dist-info/top_level.txt
slick_pay-0.3.dist-info/RECORD
